[
  {
    "id": "users.edit.heading",
    "description": "Heading for Add new user",
    "defaultMessage": "Edit user"
  },
  {
    "id": "users.edit.subheading",
    "description": "Subheading for add new user",
    "defaultMessage": "All the fields are mandatory"
  },
  {
    "id": "users.edit.userdetails.heading",
    "description": "Text for user details heading",
    "defaultMessage": "Enter User details"
  },
  {
    "id": "users.edit.userdetails.subheading",
    "description": "Text for user details subheading",
    "defaultMessage": "A User ID will be required to log into the system"
  },
  {
    "id": "users.edit.userdetails.userid",
    "description": "Text for user id",
    "defaultMessage": "User ID"
  },
  {
    "id": "users.edit.userdetails.firstname",
    "description": "Text for first name",
    "defaultMessage": "First Name"
  },
  {
    "id": "users.edit.userdetails.lastname",
    "description": "Text for last name",
    "defaultMessage": "Last Name"
  },
  {
    "id": "users.edit.roledetails.heading",
    "description": "Heading for role",
    "defaultMessage": "Choose a role"
  },
  {
    "id": "users.edit.roledetails.subheading",
    "description": "Subheading for role",
    "defaultMessage": "User will be given a specific level of control over the Butler system depending on the designated role"
  },
  {
    "id": "users.edit.roledetails.operator",
    "description": "Text for operator",
    "defaultMessage": "Operator"
  },
  {
    "id": "users.edit.roledetails.operatortext",
    "description": "Subtext for operator",
    "defaultMessage": "Grant access to the Operator Interface at each Pick Put Station in the Butler system"
  },
  {
    "id": "users.edit.roledetails.pick",
    "description": "Text for pick operator",
    "defaultMessage": "Pick Operator"
  },
  {
    "id": "users.edit.roledetails.put",
    "description": "Text for put operator",
    "defaultMessage": "Put Operator"
  },
  {
    "id": "users.edit.roledetails.audit",
    "description": "Text for audit",
    "defaultMessage": "Audit"
  },
  {
    "id": "users.edit.roledetails.supervisor",
    "description": "Text for supervisor",
    "defaultMessage": "Supervisor"
  },
  {
    "id": "users.edit.roledetails.supervisortext",
    "description": "Subtext for supervisor",
    "defaultMessage": "Grant access to the Management Interface and Operator Interface for the Butler system"
  },
  {
    "id": "users.edit.roledetails.manager",
    "description": "Text for manager",
    "defaultMessage": "Manager"
  },
  {
    "id": "users.edit.roledetails.managertext",
    "description": "Subtext for manager",
    "defaultMessage": "Grant access to the Management Interface and Operator Interface to all systems"
  },
  {
    "id": "users.edit.changepassword.heading",
    "description": "Heading for Change password",
    "defaultMessage": "Change password"
  },
  {
    "id": "users.edit.changepassword.subheading",
    "description": "Subheading for create password",
    "defaultMessage": "Min of 6 digits will be required for logging into the Operator Interface"
  },
  {
    "id": "users.edit.changepassword.field1",
    "description": "Text for password",
    "defaultMessage": "Password"
  },
  {
    "id": "users.edit.changepassword.field2",
    "description": "Text for confirm password",
    "defaultMessage": "Confirm Password"
  },
  {
    "id": "users.edit.password.",
    "description": "Heading for Password",
    "defaultMessage": "Password"
  },
  {
    "id": "users.edit.password.query",
    "description": "Text for change password",
    "defaultMessage": "Change Password?"
  },
  {
    "id": "users.edit.password.button",
    "description": "Text for edit user button",
    "defaultMessage": "Save"
  }
]